mfd_esxi/__init__.py
mfd_esxi/const.py
mfd_esxi/dswitch.py
mfd_esxi/esxi_version.py
mfd_esxi/exceptions.py
mfd_esxi/host.py
mfd_esxi/host_api.py
mfd_esxi/vm_base.py
mfd_esxi/vm_gold.py
mfd_esxi/vm_mgr.py
mfd_esxi/vmknic.py
mfd_esxi/vswitch.py
mfd_esxi/nsx/__init__.py
mfd_esxi/nsx/base.py
mfd_esxi/nsx/connection.py
mfd_esxi/nsx/enforcement_point.py
mfd_esxi/nsx/fabric_discovered_node.py
mfd_esxi/nsx/host_transport_node.py
mfd_esxi/nsx/infra_site.py
mfd_esxi/nsx/ip_pool.py
mfd_esxi/nsx/segment.py
mfd_esxi/nsx/transport_zone.py
mfd_esxi/nsx/uplink_profile.py
mfd_esxi/nsx/utils.py
mfd_esxi/nsx/vni_pool.py
mfd_esxi/vcenter/__init__.py
mfd_esxi/vcenter/cluster.py
mfd_esxi/vcenter/datacenter.py
mfd_esxi/vcenter/datastore.py
mfd_esxi/vcenter/exceptions.py
mfd_esxi/vcenter/host.py
mfd_esxi/vcenter/utils.py
mfd_esxi/vcenter/vcenter.py
mfd_esxi/vcenter/virtual_adapter.py
mfd_esxi/vcenter/virtual_machine.py
mfd_esxi/vcenter/distributed_switch/__init__.py
mfd_esxi/vcenter/distributed_switch/dswitch.py
mfd_esxi/vcenter/distributed_switch/portgroup.py
mfd_esxi/vcenter/distributed_switch/uplink.py
mfd_esxi/vcenter/virtual_switch/__init__.py
mfd_esxi/vcenter/virtual_switch/portgroup.py
mfd_esxi/vcenter/virtual_switch/vswitch.py
mfd_esxi-3.3.0.dist-info/licenses/AUTHORS.md
mfd_esxi-3.3.0.dist-info/licenses/LICENSE.md
mfd_esxi-3.3.0.dist-info/METADATA
mfd_esxi-3.3.0.dist-info/WHEEL
mfd_esxi-3.3.0.dist-info/top_level.txt
mfd_esxi-3.3.0.dist-info/RECORD
