Metadata-Version: 2.4
Name: mfd-esxi
Version: 3.3.0
Summary: Module for accessing and manipulating VMware products: ESXi, VCSA and NSX
Project-URL: Homepage, https://github.com/intel/mfd
Project-URL: Repository, https://github.com/intel/mfd-esxi
Project-URL: Issues, https://github.com/intel/mfd-esxi/issues
Project-URL: Changelog, https://github.com/intel/mfd-esxi/blob/main/CHANGELOG.md
Requires-Python: <3.14,>=3.10
License-File: LICENSE.md
License-File: AUTHORS.md
Requires-Dist: pyVmomi>=8.0.3.0.1
Requires-Dist: packaging
Requires-Dist: mfd_connect>=7.12.0
Requires-Dist: mfd_common_libs>=1.11.0
Requires-Dist: mfd_network_adapter>=14.0.0
Requires-Dist: urllib3>=2.5.0
Requires-Dist: requests
Dynamic: license-file
